ol_openedx_sentry/__init__.py
ol_openedx_sentry/app.py
ol_openedx_sentry/settings/__init__.py
ol_openedx_sentry/settings/sentry.py
ol_openedx_sentry-0.3.0.dist-info/METADATA
ol_openedx_sentry-0.3.0.dist-info/WHEEL
ol_openedx_sentry-0.3.0.dist-info/entry_points.txt
ol_openedx_sentry-0.3.0.dist-info/licenses/LICENSE.txt
ol_openedx_sentry-0.3.0.dist-info/RECORD
