Metadata-Version: 2.4
Name: ol-openedx-sentry
Version: 0.3.0
Summary: An Open edX plugin to enable error tracking with Sentry
Author: MIT Office of Digital Learning
License-Expression: BSD-3-Clause
License-File: LICENSE.txt
Requires-Python: >=3.11
Requires-Dist: django>=4.0
Requires-Dist: sentry-sdk>=2.0.0
